Metadata-Version: 2.4
Name: PyPcre
Version: 0.2.8
Summary: Modern, GIL-friendly, Fast Python bindings for PCRE2 with auto caching and JIT of compiled patterns.
Author-email: ModelCloud <qubitium@modelcloud.ai>
License-Expression: Apache-2.0
Project-URL: Homepage, https://github.com/ModelCloud/pcre
Keywords: regex,pcre2,bindings
Classifier: Programming Language :: Python :: 3
Classifier: Programming Language :: Python :: 3 :: Only
Classifier: Programming Language :: Python :: 3.10
Classifier: Programming Language :: Python :: 3.11
Classifier: Programming Language :: Python :: 3.12
Classifier: Programming Language :: Python :: 3.13
Classifier: Programming Language :: Python :: 3.14
Classifier: Programming Language :: C
Classifier: Topic :: Software Development :: Libraries
Classifier: Topic :: Text Processing :: Linguistic
Requires-Python: >=3.9
License-File: LICENSE
Dynamic: license-file
